Metadata-Version: 2.1
Name: cjpscripts
Version: 0.1.1
Summary: My Personal Script
Author: Cai Jianping
Author-email: jpingcai@163.com
License: MIT Licence
Keywords: database,localServer
Platform: any
License-File: LICENSE
